.stestr.conf
AUTHORS
ChangeLog
LICENSE
README.md
requirements.txt
setup.cfg
setup.py
test-requirements.txt
tox.ini
.github/workflows/tests.yaml
etc/interfaces.yaml
sriov_netplan_shim/__init__.py
sriov_netplan_shim/cmd.py
sriov_netplan_shim/pci.py
sriov_netplan_shim.egg-info/PKG-INFO
sriov_netplan_shim.egg-info/SOURCES.txt
sriov_netplan_shim.egg-info/dependency_links.txt
sriov_netplan_shim.egg-info/entry_points.txt
sriov_netplan_shim.egg-info/not-zip-safe
sriov_netplan_shim.egg-info/pbr.json
sriov_netplan_shim.egg-info/requires.txt
sriov_netplan_shim.egg-info/top_level.txt
sriov_netplan_shim/tests/__init__.py
sriov_netplan_shim/tests/unit/__init__.py
sriov_netplan_shim/tests/unit/pci_responses.py
sriov_netplan_shim/tests/unit/test_pci.py
sriov_netplan_shim/tests/unit/test_pci_helper.py
sriov_netplan_shim/tests/unit/test_utils.py
tools/sriov-netplan-shim.service