Metadata-Version: 2.1
Name: sriov-netplan-shim
Version: 0.1.4
Summary: Utility to configure SR-IOV VF's (until netplan can do it)
Home-page: http://github.com/openstack-charmers/sriov-netplan-shim
Author: OpenStack Charmers Team
Author-email: james.page@ubuntu.com
License: UNKNOWN
Platform: UNKNOWN
Classifier: Intended Audience :: Information Technology
Classifier: Intended Audience :: System Administrators
Classifier: License :: OSI Approved :: Apache Software License
Classifier: Operating System :: POSIX :: Linux
Classifier: Programming Language :: Python
Classifier: Programming Language :: Python :: 3
Classifier: Programming Language :: Python :: 3.5
Classifier: Programming Language :: Python :: 3.6
Classifier: Programming Language :: Python :: 3.7
